Metadata-Version: 2.0
Name: odoo9-addon-analytic-operating-unit
Version: 9.0.1.0.0
Summary: Analytic Operating Unit
Home-page: https://github.com/OCA/operating-unit
Author: Eficent, Odoo Community Association (OCA)
Author-email: support@odoo-community.org
License: LGPL-3
Platform: UNKNOWN
Requires-Dist: odoo (<9.1a,>=9.0a)
Requires-Dist: odoo9-addon-operating-unit
Classifier: Programming Language :: Python :: 2.7
Classifier: Framework :: Odoo
Classifier: License :: OSI Approved :: GNU Lesser General Public License v3 (LGPLv3)
